{"nodes": [{"id": "ui_visualization_api_clear_screen_py", "label": "clear_screen.py", "file_type": "code", "source_file": "ui\\visualization_api\\clear_screen.py", "source_location": "L1"}, {"id": "clear_screen_build_payload", "label": "_build_payload()", "file_type": "code", "source_file": "ui\\visualization_api\\clear_screen.py", "source_location": "L4"}, {"id": "clear_screen_clear_screen", "label": "_clear_screen()", "file_type": "code", "source_file": "ui\\visualization_api\\clear_screen.py", "source_location": "L8"}, {"id": "clear_screen_rationale_9", "label": "Clear all visual elements on screen.    Args:       host (str, optional): Ser", "file_type": "rationale", "source_file": "ui\\visualization_api\\clear_screen.py", "source_location": "L9"}], "edges": [{"source": "ui_visualization_api_clear_screen_py", "target": "ui_visualization_api_client", "relation": "imports_from", "confidence": "EXTRACTED", "source_file": "ui\\visualization_api\\clear_screen.py", "source_location": "L1", "weight": 1.0}, {"source": "ui_visualization_api_clear_screen_py", "target": "core_registry", "relation": "imports_from", "confidence": "EXTRACTED", "source_file": "ui\\visualization_api\\clear_screen.py", "source_location": "L2", "weight": 1.0}, {"source": "ui_visualization_api_clear_screen_py", "target": "clear_screen_build_payload", "relation": "contains", "confidence": "EXTRACTED", "source_file": "ui\\visualization_api\\clear_screen.py", "source_location": "L4", "weight": 1.0}, {"source": "ui_visualization_api_clear_screen_py", "target": "clear_screen_clear_screen", "relation": "contains", "confidence": "EXTRACTED", "source_file": "ui\\visualization_api\\clear_screen.py", "source_location": "L8", "weight": 1.0}, {"source": "clear_screen_clear_screen", "target": "clear_screen_build_payload", "relation": "calls", "confidence": "EXTRACTED", "source_file": "ui\\visualization_api\\clear_screen.py", "source_location": "L16", "weight": 1.0}, {"source": "clear_screen_rationale_9", "target": "clear_screen_clear_screen", "relation": "rationale_for", "confidence": "EXTRACTED", "source_file": "ui\\visualization_api\\clear_screen.py", "source_location": "L9", "weight": 1.0}]}